LICENSE
README.md
setup.py
tests/__init__.py
tests/dao/__init__.py
tests/dao/test_mysql_dao.py
tests/gslib/__init__.py
tests/gslib/test_credit_code.py
tests/gslib/test_org_code.py
tests/gslib/test_reg_number.py
wbximy_common/__init__.py
wbximy_common.egg-info/PKG-INFO
wbximy_common.egg-info/SOURCES.txt
wbximy_common.egg-info/dependency_links.txt
wbximy_common.egg-info/top_level.txt
wbximy_common/clients/__init__.py
wbximy_common/clients/kafka_client.py
wbximy_common/clients/mysql_client.py
wbximy_common/clients/sqlite_client.py
wbximy_common/clients/tunnel.py
wbximy_common/clients/redis/__init__.py
wbximy_common/clients/redis/_redis.py
wbximy_common/clients/redis/redis_hash.py
wbximy_common/clients/redis/redis_queue.py
wbximy_common/dao/__init__.py
wbximy_common/dao/base_entity.py
wbximy_common/dao/mysql_dao.py
wbximy_common/dao/mysql_sharding_dao.py
wbximy_common/dao/sqlite_dao.py
wbximy_common/gslib/__init__.py
wbximy_common/gslib/credit_code.py
wbximy_common/gslib/org_code.py
wbximy_common/gslib/reg_number.py
wbximy_common/libs/__init__.py
wbximy_common/libs/collection.py
wbximy_common/libs/concurrent.py
wbximy_common/libs/dt.py
wbximy_common/libs/env.py
wbximy_common/libs/log.py
wbximy_common/libs/req.py