Metadata-Version: 2.1
Name: wbximy-common
Version: 0.0.2
Summary: common tools wbximy.
Home-page: https://github.com/shine4u/wbximy-common
Author: WangBangXu
Author-email: shine19890705@gmail.com
Classifier: Programming Language :: Python :: 3
Classifier: License :: OSI Approved :: MIT License
Classifier: Operating System :: OS Independent
Requires-Python: >=3.9
License-File: LICENSE
